{
    "Chapter14Shop": {
        "action": "DoNothing",
        "next": [
            "[JumpBack]MerchantBuy14.1",
            "[JumpBack]MerchantBuy14.2",
            "[JumpBack]MerchantBuy14.3"
        ],
        "max_hit": 1,
        "timeout": 8000
    },
    "MerchantBuy14.1": {
        "action": "Click",
        "next": [
            "Arbitrage_Merchant_BuyMsg",
            "MerchantBuy14.1"
        ],
        "post_delay": 1000,
        "recognition": "TemplateMatch",
        "roi": [
            401,
            103,
            71,
            72
        ],
        "template": "Shop/Almond.png",
        "doc": "杏仁,100",
        "threshold": 0.9,
        "max_hit": 1,
        "timeout": 2000
    },
    "MerchantBuy14.2": {
        "action": "Click",
        "next": [
            "Arbitrage_Merchant_BuyMsg",
            "MerchantBuy14.2"
        ],
        "post_delay": 1000,
        "recognition": "TemplateMatch",
        "roi": [
            398,
            279,
            76,
            73
        ],
        "template": "Shop/Butter.png",
        "doc": "黄油,400",
        "threshold": 0.9,
        "max_hit": 1,
        "timeout": 2000
    },
    "MerchantBuy14.3": {
        "action": "Click",
        "next": [
            "Arbitrage_Merchant_BuyMsg",
            "MerchantBuy14.3"
        ],
        "post_delay": 1000,
        "recognition": "TemplateMatch",
        "roi": [
            398,
            366,
            76,
            76
        ],
        "template": "Shop/Sugar.png",
        "doc": "白糖,400",
        "threshold": 0.9,
        "max_hit": 1,
        "timeout": 2000
    }
}