{
    "Chapter5Shop": {
        "action": "DoNothing",
        "next": [
            "[JumpBack]MerchantBuy5.1",
            "[JumpBack]MerchantBuy5.2",
            "[JumpBack]MerchantBuy5.3"
        ],
        "max_hit": 1,
        "timeout": 8000
    },
    "MerchantBuy5.1": {
        "action": "Click",
        "next": [
            "Arbitrage_Merchant_BuyMsg",
            "MerchantBuy5.1"
        ],
        "post_delay": 1000,
        "recognition": "TemplateMatch",
        "roi": [
            401,
            103,
            71,
            72
        ],
        "template": "Shop/HamiMelon.png",
        "doc": "哈密瓜,400",
        "threshold": 0.9,
        "max_hit": 1,
        "timeout": 2000
    },
    "MerchantBuy5.2": {
        "action": "Click",
        "next": [
            "Arbitrage_Merchant_BuyMsg",
            "MerchantBuy5.2"
        ],
        "post_delay": 1000,
        "recognition": "TemplateMatch",
        "roi": [
            930,
            103,
            77,
            74
        ],
        "template": "Shop/Sugar.png",
        "doc": "白糖,400",
        "threshold": 0.9,
        "max_hit": 1,
        "timeout": 2000
    },
    "MerchantBuy5.3": {
        "action": "Click",
        "next": [
            "Arbitrage_Merchant_BuyMsg",
            "MerchantBuy5.3"
        ],
        "post_delay": 1000,
        "recognition": "TemplateMatch",
        "roi": [
            398,
            279,
            76,
            73
        ],
        "template": "Shop/Saffron.png",
        "doc": "藏红花,400",
        "threshold": 0.9,
        "max_hit": 1,
        "timeout": 2000
    }
}